osaapi/__init__.py
osaapi-1.0.1.dist-info/LICENSE
osaapi-1.0.1.dist-info/METADATA
osaapi-1.0.1.dist-info/WHEEL
osaapi-1.0.1.dist-info/RECORD
