Metadata-Version: 2.1
Name: osaapi
Version: 1.0.1
Summary: 
Author: Ingrammicro Inc.
Requires-Python: >=3.7,<3.9
Classifier: Programming Language :: Python :: 3
Classifier: Programming Language :: Python :: 3.7
Classifier: Programming Language :: Python :: 3.8
